Products.ZAlchemyConnector-1.0.4-py3.7-nspkg.pth
Products/ZAlchemyConnector/Query.py
Products/ZAlchemyConnector/Wrapper.py
Products/ZAlchemyConnector/__init__.py
Products.ZAlchemyConnector-1.0.4.dist-info/LICENSE
Products.ZAlchemyConnector-1.0.4.dist-info/METADATA
Products.ZAlchemyConnector-1.0.4.dist-info/WHEEL
Products.ZAlchemyConnector-1.0.4.dist-info/namespace_packages.txt
Products.ZAlchemyConnector-1.0.4.dist-info/top_level.txt
Products.ZAlchemyConnector-1.0.4.dist-info/RECORD
