Metadata-Version: 2.1
Name: Products.ZAlchemyConnector
Version: 1.0.4
Summary: Connector and Query object for zope & sqlalchemy
Home-page: https://github.com/huine/Products.ZAlchemyConnector
Author: Gabriel Diniz Gisoldo
Author-email: gabrielgisoldi@gmail.com
License: UNKNOWN
Keywords: Zope Database adapter SQLAlchemy
Platform: UNKNOWN
Classifier: Development Status :: 5 - Production/Stable
Classifier: Intended Audience :: Developers
Classifier: Environment :: Web Environment
Classifier: Framework :: Zope
Classifier: Framework :: Zope :: 4
Classifier: Framework :: Zope :: 5
Classifier: License :: OSI Approved :: MIT License
Classifier: Operating System :: OS Independent
Classifier: Programming Language :: Python
Classifier: Programming Language :: Python :: 3.7
Classifier: Topic :: Database
Classifier: Topic :: Database :: Front-Ends
Classifier: Topic :: Software Development :: Libraries :: Python Modules
Requires-Python: >=3.7
Requires-Dist: setuptools
Requires-Dist: z3c.sqlalchemy (>1.5.1)
Requires-Dist: SQLAlchemy (>=0.5.5)
Requires-Dist: zope.sqlalchemy (>=1.2.0)
Requires-Dist: zope.component
Requires-Dist: zope.interface
Requires-Dist: zope.testing
Requires-Dist: zope.schema
